{
  "generatedAt": "2026-05-30T07:46:02.290Z",
  "youtube": {
    "status": "ok",
    "lastFetchedAt": "2026-05-30T04:14:30.837Z",
    "channel": {
      "id": "UC0ubM_L6ISEgqr5SJfI8XTA",
      "title": "Daan Willems Automotive",
      "description": "Backstage content @ DWA",
      "customUrl": "@daanwillemsautomotive",
      "thumbnail": "/images/socials/avatars/youtube.jpg",
      "subscriberCount": 33100,
      "videoCount": 45,
      "viewCount": 3564090,
      "bannerUrl": "https://yt3.googleusercontent.com/n2yJgGUAPlCi5Zv5tB6NflWMNyuRXIEj7dM30IeQ6BDW0nnUjOXbABuj4qIPUmtBr8InSej5"
    },
    "latest": [
      {
        "id": "ghNYgBLRtEQ",
        "url": "https://www.youtube.com/watch?v=ghNYgBLRtEQ",
        "title": "WORDT DIT DE GEKSTE ZOMER OOIT!? + AUTO SLOPEN!! VLOG #34",
        "description": "Welkom op het officiele Youtube-kanaal van Daan Willems! Krijg een unieke kijk in het werk en privéleven van Daan Willems.",
        "publishedAt": "2026-05-24T09:00:06Z",
        "thumbnail": "https://i.ytimg.com/vi/ghNYgBLRtEQ/hqdefault.jpg",
        "viewCount": 52363,
        "likeCount": 940,
        "durationSec": 916
      },
      {
        "id": "aGHKZA8XKZk",
        "url": "https://www.youtube.com/watch?v=aGHKZA8XKZk",
        "title": "DAAN HEEFT RUZIE MET KLANT!!! EN SLOOPT AUTO?! VLOG #33",
        "description": "Welkom op het officiele Youtube-kanaal van Daan Willems! Krijg een unieke kijk in het werk en privéleven van Daan Willems.",
        "publishedAt": "2026-05-17T08:42:44Z",
        "thumbnail": "https://i.ytimg.com/vi/aGHKZA8XKZk/hqdefault.jpg",
        "viewCount": 76313,
        "likeCount": 2588,
        "durationSec": 1282
      },
      {
        "id": "YZpn2Awy3pY",
        "url": "https://www.youtube.com/watch?v=YZpn2Awy3pY",
        "title": "ORDINAIR ZUIPEN IN AMSTERDAM MET BN&#39;ERS VLOG #32",
        "description": "DAAN WILLEMS AUTOMOTIVE In- en verkoop occasions Detailen Reparatie & onderhoud CAMERA MAN PLUS ...",
        "publishedAt": "2026-05-13T15:38:57Z",
        "thumbnail": "https://i.ytimg.com/vi/YZpn2Awy3pY/hqdefault.jpg",
        "viewCount": 97862,
        "likeCount": 2063,
        "durationSec": 1125
      },
      {
        "id": "trhUPk1nm7s",
        "url": "https://www.youtube.com/watch?v=trhUPk1nm7s",
        "title": "ONVOORBEREID HET PODIUM OP?! DAAN WILLEMS ALS DJI!! VLOG #31",
        "description": "DAAN WILLEMS AUTOMOTIVE In- en verkoop occasions Detailen Reparatie & onderhoud CAMERAMAN + ...",
        "publishedAt": "2026-05-06T15:01:48Z",
        "thumbnail": "https://i.ytimg.com/vi/trhUPk1nm7s/hqdefault.jpg",
        "viewCount": 53354,
        "likeCount": 1150,
        "durationSec": 913
      },
      {
        "id": "9jrDcE2YXOk",
        "url": "https://www.youtube.com/watch?v=9jrDcE2YXOk",
        "title": "DIT HAD IK NIET VERWACHT... AUTO TAXEREN + MOTORRIJDEN!! VLOG #30",
        "description": "DAAN WILLEMS AUTOMOTIVE In- en verkoop occasions Detailen Reparatie & onderhoud CAMERAMAN: ...",
        "publishedAt": "2026-05-03T09:00:24Z",
        "thumbnail": "https://i.ytimg.com/vi/9jrDcE2YXOk/hqdefault.jpg",
        "viewCount": 48638,
        "likeCount": 956,
        "durationSec": 1241
      },
      {
        "id": "5zRc2eCIlS0",
        "url": "https://www.youtube.com/watch?v=5zRc2eCIlS0",
        "title": "DAAN WILLEMS DRAAIT DOOR!! (STUNTPILOOT) + €500 BESTELLING WEGBRENGEN!! VLOG #29",
        "description": "DAAN WILLEMS AUTOMOTIVE In- en verkoop occasions Detailen Reparatie & onderhoud cameraman+editor ...",
        "publishedAt": "2026-04-29T15:00:09Z",
        "thumbnail": "https://i.ytimg.com/vi/5zRc2eCIlS0/hqdefault.jpg",
        "viewCount": 63484,
        "likeCount": 1116,
        "durationSec": 1129
      }
    ],
    "top": [
      {
        "id": "9vBJKYhhptM",
        "url": "https://www.youtube.com/watch?v=9vBJKYhhptM",
        "title": "RAUL GROENEN &amp; DAAN WILLEMS MAKEN CHAOS IN EINDHOVEN!! WERKELIJK IETS APARTS!!! VLOG #16",
        "description": "DAAN WILLEMS AUTOMOTIVE In- en verkoop occasions Detailen Reparatie & onderhoud Bekijk aanbod ...",
        "publishedAt": "2026-03-09T17:26:22Z",
        "thumbnail": "https://i.ytimg.com/vi/9vBJKYhhptM/hqdefault.jpg",
        "viewCount": 172715,
        "likeCount": 4131,
        "durationSec": 713
      },
      {
        "id": "N2Mr3ddlArc",
        "url": "https://www.youtube.com/watch?v=N2Mr3ddlArc",
        "title": "Taxatie loopt uit de hand? Langs bij Danny van House of Cars | DWA",
        "description": "Abonneer voor meer backstage content @ Daan Willems Automotive Emblemen Oeteldonk ...",
        "publishedAt": "2025-12-07T08:00:35Z",
        "thumbnail": "https://i.ytimg.com/vi/N2Mr3ddlArc/hqdefault.jpg",
        "viewCount": 148345,
        "likeCount": 4011,
        "durationSec": 858
      },
      {
        "id": "AB2L1OJD_PA",
        "url": "https://www.youtube.com/watch?v=AB2L1OJD_PA",
        "title": "DAAN NAAR DE KAMASUTRA BEURS, GAAT FOUT!! DEEL 1 VLOG #20",
        "description": "DAAN WILLEMS AUTOMOTIVE In- en verkoop occasions Detailen Reparatie & onderhoud CAMERAMAN + ...",
        "publishedAt": "2026-03-29T09:20:30Z",
        "thumbnail": "https://i.ytimg.com/vi/AB2L1OJD_PA/hqdefault.jpg",
        "viewCount": 125015,
        "likeCount": 2013,
        "durationSec": 1201
      },
      {
        "id": "KTJRmjAvIPg",
        "url": "https://www.youtube.com/watch?v=KTJRmjAvIPg",
        "title": "DAAN IS BOOS!!! &amp; BMW TAXEREN GAAT FOUT, VLOG #13",
        "description": "DAAN WILLEMS AUTOMOTIVE In- en verkoop occasions Detailen Reparatie & onderhoud CAMERA MAN ...",
        "publishedAt": "2026-02-25T16:05:56Z",
        "thumbnail": "https://i.ytimg.com/vi/KTJRmjAvIPg/hqdefault.jpg",
        "viewCount": 119932,
        "likeCount": 1818,
        "durationSec": 834
      },
      {
        "id": "wm0R5AMYmig",
        "url": "https://www.youtube.com/watch?v=wm0R5AMYmig",
        "title": "DAAN &amp; DANNY GAAN OFFROAD MET SUZUKI ALTO // GAAT FOUT!!!!! VLOG #22",
        "description": "DAAN WILLEMS AUTOMOTIVE In- en verkoop occasions Detailen Reparatie & onderhoud Cameraman ...",
        "publishedAt": "2026-04-05T06:45:03Z",
        "thumbnail": "https://i.ytimg.com/vi/wm0R5AMYmig/hqdefault.jpg",
        "viewCount": 112664,
        "likeCount": 2682,
        "durationSec": 1626
      },
      {
        "id": "h3Yjlt1tr4A",
        "url": "https://www.youtube.com/watch?v=h3Yjlt1tr4A",
        "title": "Raúl Groenen op bezoek, kantoor bouwen en langs bij Keukensale Den Bosch | DWA Vlog #3",
        "description": "Abonneer voor meer backstage content @ Daan Willems Automotive In deze video: Van De Pol Bouw- en Timmerwerken ...",
        "publishedAt": "2025-12-20T09:30:24Z",
        "thumbnail": "https://i.ytimg.com/vi/h3Yjlt1tr4A/hqdefault.jpg",
        "viewCount": 111803,
        "likeCount": 1728,
        "durationSec": 694
      }
    ],
    "lastSuccessAt": "2026-05-30T04:14:30.837Z"
  },
  "tiktok": {
    "status": "ok",
    "lastFetchedAt": "2026-05-30T04:33:19.417Z",
    "handle": "daanwillemsautomotive",
    "profile": {
      "uniqueId": "daanwillemsautomotive",
      "nickname": "Daan Willems",
      "bio": "𝐃𝐀𝐀𝐍 𝐖𝐈𝐋𝐋𝐄𝐌𝐒 𝐀𝐔𝐓𝐎𝐌𝐎𝐓𝐈𝐕𝐄\nIn- en verkoop occasions \nReparatie & onderhoud",
      "bioLink": "https://linktr.ee/daanwillems_automotive",
      "avatar": "/images/socials/avatars/tiktok.jpg",
      "verified": false,
      "url": "https://www.tiktok.com/@daanwillemsautomotive"
    },
    "stats": {
      "followerCount": 123100,
      "followingCount": 11,
      "heartCount": 2100000,
      "videoCount": 87
    },
    "videos": [],
    "lastSuccessAt": "2026-05-30T04:33:19.417Z"
  },
  "instagram": {
    "status": "ok",
    "lastFetchedAt": "2026-05-30T07:44:48.202Z",
    "handle": "daanwillemsautomotive",
    "lastSuccessAt": "2026-05-30T07:46:01.728Z",
    "lastProfileFetchAt": "2026-05-30T07:44:48.203Z",
    "profile": {
      "userId": "53052746898",
      "username": "daanwillemsautomotive",
      "fullName": "Daan Willems Automotive",
      "bio": "𝐃𝐀𝐀𝐍 𝐖𝐈𝐋𝐋𝐄𝐌𝐒 𝐀𝐔𝐓𝐎𝐌𝐎𝐓𝐈𝐕𝐄\nIn- en verkoop occasions\nReparatie & onderhoud",
      "bioLinks": [
        {
          "title": "",
          "url": "https://www.daanwillemsautomotiveshop.nl"
        },
        {
          "title": "",
          "url": "https://linktr.ee/daanwillems_automotive"
        }
      ],
      "externalUrl": "https://www.daanwillemsautomotiveshop.nl/",
      "avatar": "/images/socials/avatars/instagram.jpg",
      "isBusiness": true,
      "category": "Car dealership",
      "verified": false,
      "url": "https://www.instagram.com/daanwillemsautomotive/"
    },
    "stats": {
      "followerCount": 133681,
      "followingCount": 36,
      "mediaCount": 91,
      "totalPlays": 53766791,
      "totalLikes": 1161427,
      "totalComments": 13361,
      "sampledPostCount": 12,
      "profileSourcedFromPrev": true,
      "feedSourcedFromPrev": true,
      "iteratorCycleComplete": false
    },
    "posts": [
      {
        "id": "DY6x5zRIgDS",
        "shortcode": "DY6x5zRIgDS",
        "url": "https://www.instagram.com/p/DY6x5zRIgDS/",
        "type": "reel",
        "publishedAt": "2026-05-29T10:02:01.000Z",
        "thumbnail": "/images/socials/ig-posts/DY6x5zRIgDS.jpg",
        "caption": "Ford Ka • Origineel Nederlands • Airco • Lage kilometerstand •\n\nInteresse DM❗️\n\nOutfit: @jorcustom \nKORTINGSCODE: Daan15\n\n#daanwillemsautomotive #auto #occasion #autodealer",
        "likeCount": 6339,
        "commentCount": 103,
        "viewCount": 216918
      },
      {
        "id": "DY4wYcnKwSx",
        "shortcode": "DY4wYcnKwSx",
        "url": "https://www.instagram.com/p/DY4wYcnKwSx/",
        "type": "reel",
        "publishedAt": "2026-05-28T15:09:21.000Z",
        "thumbnail": "/images/socials/ig-posts/DY4wYcnKwSx.jpg",
        "caption": "Deze hadden jullie nog van ons tegoed #humor",
        "likeCount": 4085,
        "commentCount": 25,
        "viewCount": 186267
      },
      {
        "id": "DYzElRWIeFw",
        "shortcode": "DYzElRWIeFw",
        "url": "https://www.instagram.com/p/DYzElRWIeFw/",
        "type": "reel",
        "publishedAt": "2026-05-26T10:10:47.000Z",
        "thumbnail": "/images/socials/ig-posts/DYzElRWIeFw.jpg",
        "caption": "Dit wil je niet missen... 👀🔥\nDe volledige video staat nu op ons\nYouTube-kanaal!\n\nCheck de link in bio🔗\n\nOutfit: @jorcustom \nKORTINGSCODE: Daan15\n\n#daanwillemsautomotive #automotive\n#linkinbio #auto #humor",
        "likeCount": 5065,
        "commentCount": 40,
        "viewCount": 289655
      },
      {
        "id": "DYrOtj2oSnr",
        "shortcode": "DYrOtj2oSnr",
        "url": "https://www.instagram.com/p/DYrOtj2oSnr/",
        "type": "reel",
        "publishedAt": "2026-05-23T09:05:13.000Z",
        "thumbnail": "/images/socials/ig-posts/DYrOtj2oSnr.jpg",
        "caption": "Gebruik KORTINGSCODE “Daan15” voor 15% korting bij @jorcustom en maak kans op €1500 shoptegoed!!👀🔥\n\n#daanwillemsautomotive #auto #kleding #kortingscode  #autodealer",
        "likeCount": 1290,
        "commentCount": 14,
        "viewCount": 138204
      },
      {
        "id": "DYovYXyow_o",
        "shortcode": "DYovYXyow_o",
        "url": "https://www.instagram.com/p/DYovYXyow_o/",
        "type": "reel",
        "publishedAt": "2026-05-22T09:53:00.000Z",
        "thumbnail": "/images/socials/ig-posts/DYovYXyow_o.jpg",
        "caption": "Cheerio 🎶 \n\nWerkelijk iets aparts❗️\n\n#foryou #cheerio #daanwillemsautomotive #auto #automotive",
        "likeCount": 16649,
        "commentCount": 343,
        "viewCount": 381824
      },
      {
        "id": "DYhCp9Eo3Ih",
        "shortcode": "DYhCp9Eo3Ih",
        "url": "https://www.instagram.com/p/DYhCp9Eo3Ih/",
        "type": "reel",
        "publishedAt": "2026-05-19T10:12:55.000Z",
        "thumbnail": "/images/socials/ig-posts/DYhCp9Eo3Ih.jpg",
        "caption": "Dit wil je niet missen… 👀🔥\nDe volledige video staat nu op ons YouTube-kanaal! 🎥\n\nCheck de link in bio 🔗\n\nOutfit: @jorcustom KORTINGSCODE: Daan15 \n\n#daanwillemsautomotive #automotive #linkinbio #auto #humor",
        "likeCount": 65743,
        "commentCount": 594,
        "viewCount": 1183354
      }
    ],
    "iterator": {
      "startedAt": "2026-05-30T07:44:48.554Z",
      "lastFetchedAt": "2026-05-30T07:46:01.728Z",
      "completedAt": null,
      "cursor": "3889723293121066135_4621301659",
      "items": {
        "3907655103034818770": {
          "pk": "3907655103034818770",
          "code": "DY6x5zRIgDS",
          "takenAt": 1780048921,
          "mediaType": 2,
          "productType": "clips",
          "likeCount": 6339,
          "commentCount": 103,
          "playCount": 216918,
          "thumbnail": "https://scontent-sjc6-1.cdninstagram.com/v/t51.82787-15/707946369_18050148398770899_2348394615023492332_n.jpg?stp=dst-jpg_e15_tt6&_nc_cat=107&ig_cache_key=MzkwNzY1NTEwMzAzNDgxODc3MDE4MDUwMTQ4Mzk1NzcwODk5.3-ccb7-5&ccb=7-5&_nc_sid=58cdad&efg=eyJ2ZW5jb2RlX3RhZyI6IkNMSVBTLnhwaWRzLjcyMC5zZHIudmlkZW9fZGVmYXVsdF9jb3Zlcl9mcmFtZS5DMyJ9&_nc_ohc=AcgiPaC30bcQ7kNvwGOzVbd&_nc_oc=AdqNfAJbCzXWyz9_hP6R6x1YSSD0hyN0c2tDlpVuMSJStEYxabNxDKz2aUT-jkwRu8U&_nc_ad=z-m&_nc_cid=0&_nc_zt=23&_nc_ht=scontent-sjc6-1.cdninstagram.com&_nc_gid=JMD35m94F_b7pOx4A6UHWg&_nc_ss=7a120&oh=00_Af4-SyKoCTPbEQzU9RW3XdwZGQsk3MCAru5KOg-HJAh3BA&oe=6A205EDF",
          "caption": "Ford Ka • Origineel Nederlands • Airco • Lage kilometerstand •\n\nInteresse DM❗️\n\nOutfit: @jorcustom \nKORTINGSCODE: Daan15\n\n#daanwillemsautomotive #auto #occasion #autodealer"
        },
        "3907085462965781681": {
          "pk": "3907085462965781681",
          "code": "DY4wYcnKwSx",
          "takenAt": 1779980961,
          "mediaType": 2,
          "productType": "clips",
          "likeCount": 4085,
          "commentCount": 25,
          "playCount": 186267,
          "thumbnail": "https://scontent-sjc6-1.cdninstagram.com/v/t51.71878-15/708005546_1286369483660595_1168920900586593906_n.jpg?stp=dst-jpg_e15_tt6&_nc_cat=101&ig_cache_key=MzkwNzA4NTQ2Mjk2NTc4MTY4MQ%3D%3D.3-ccb7-5&ccb=7-5&_nc_sid=58cdad&efg=eyJ2ZW5jb2RlX3RhZyI6IkNMSVBTLnhwaWRzLjY0MC5zZHIudmlkZW9fbmZyYW1lX2NvdmVyX2ZyYW1lLkMzIn0%3D&_nc_ohc=l0SnrtSkegAQ7kNvwHCiqBf&_nc_oc=AdoroDTPfbKitNRSQ5gY6w-Kx0nuKQfhOr7ezCVfSW3iVEetyr0Kn9fq0P2y5BU8DXg&_nc_ad=z-m&_nc_cid=0&_nc_zt=23&_nc_ht=scontent-sjc6-1.cdninstagram.com&_nc_gid=JMD35m94F_b7pOx4A6UHWg&_nc_ss=7a120&oh=00_Af5VWhItM1meWDFgaSxaSocGMFsHeHiTPpcI5ogqtp9weQ&oe=6A20526F",
          "caption": "Deze hadden jullie nog van ons tegoed #humor"
        },
        "3905485455291965808": {
          "pk": "3905485455291965808",
          "code": "DYzElRWIeFw",
          "takenAt": 1779790247,
          "mediaType": 2,
          "productType": "clips",
          "likeCount": 5065,
          "commentCount": 40,
          "playCount": 289655,
          "thumbnail": "https://scontent-sjc3-1.cdninstagram.com/v/t51.71878-15/706849839_1498460881957227_7845344164020509459_n.jpg?stp=dst-jpg_e15_tt6&_nc_cat=110&ig_cache_key=MzkwNTQ4NTQ1NTI5MTk2NTgwOA%3D%3D.3-ccb7-5&ccb=7-5&_nc_sid=58cdad&efg=eyJ2ZW5jb2RlX3RhZyI6IkNMSVBTLnhwaWRzLjY0MC5zZHIudmlkZW9fbmZyYW1lX2NvdmVyX2ZyYW1lLkMzIn0%3D&_nc_ohc=5eSnFoEMOB8Q7kNvwHc4r4v&_nc_oc=Adoz0oNZ35mNRnxM-pg8ZOn8RdOq1y8xdHLsQarbngazMErayD78qBwPvcI7K-zD3bw&_nc_ad=z-m&_nc_cid=0&_nc_zt=23&_nc_ht=scontent-sjc3-1.cdninstagram.com&_nc_gid=JMD35m94F_b7pOx4A6UHWg&_nc_ss=7a120&oh=00_Af6Hh7xixh8lTZ7wDt6MhoKh7_irOedUt5tEnrPnzaSnQA&oe=6A205BA9",
          "caption": "Dit wil je niet missen... 👀🔥\nDe volledige video staat nu op ons\nYouTube-kanaal!\n\nCheck de link in bio🔗\n\nOutfit: @jorcustom \nKORTINGSCODE: Daan15\n\n#daanwillemsautomotive #automotive\n#linkinbio #auto #humor"
        },
        "3903278205571770859": {
          "pk": "3903278205571770859",
          "code": "DYrOtj2oSnr",
          "takenAt": 1779527113,
          "mediaType": 2,
          "productType": "clips",
          "likeCount": 1290,
          "commentCount": 14,
          "playCount": 138204,
          "thumbnail": "https://scontent-sjc6-1.cdninstagram.com/v/t51.71878-15/705757843_1340140798254473_6176862483050917538_n.jpg?stp=dst-jpg_e15_tt6&_nc_cat=104&ig_cache_key=MzkwMzI3ODIwNTU3MTc3MDg1OQ%3D%3D.3-ccb7-5&ccb=7-5&_nc_sid=58cdad&efg=eyJ2ZW5jb2RlX3RhZyI6IkNMSVBTLnhwaWRzLjY0MC5zZHIudmlkZW9fbmZyYW1lX2NvdmVyX2ZyYW1lLkMzIn0%3D&_nc_ohc=nCO_sABnLuQQ7kNvwHLwMZ5&_nc_oc=AdoZIZ3GNvk5HwAb2D71ZcTICo0VfsUeGOaC5b27GT95uDsZly7yVPeH9qPoo6CKgQU&_nc_ad=z-m&_nc_cid=0&_nc_zt=23&_nc_ht=scontent-sjc6-1.cdninstagram.com&_nc_gid=JMD35m94F_b7pOx4A6UHWg&_nc_ss=7a120&oh=00_Af58dK1J6DnyDDnk8KjnnB9C4DVTXFkPRxFQoXPlpA8XFg&oe=6A20621A",
          "caption": "Gebruik KORTINGSCODE “Daan15” voor 15% korting bij @jorcustom en maak kans op €1500 shoptegoed!!👀🔥\n\n#daanwillemsautomotive #auto #kleding #kortingscode  #autodealer"
        },
        "3902577460115607528": {
          "pk": "3902577460115607528",
          "code": "DYovYXyow_o",
          "takenAt": 1779443580,
          "mediaType": 2,
          "productType": "clips",
          "likeCount": 16649,
          "commentCount": 343,
          "playCount": 381824,
          "thumbnail": "https://scontent-sjc6-1.cdninstagram.com/v/t51.71878-15/703762778_1005843681872906_884986882806364445_n.jpg?stp=dst-jpg_e15_tt6&_nc_cat=102&ig_cache_key=MzkwMjU3NzQ2MDExNTYwNzUyOA%3D%3D.3-ccb7-5&ccb=7-5&_nc_sid=58cdad&efg=eyJ2ZW5jb2RlX3RhZyI6IkNMSVBTLnhwaWRzLjY0MC5zZHIudmlkZW9fZGVmYXVsdF9jb3Zlcl9mcmFtZS5DMyJ9&_nc_ohc=NrKfRNqkydgQ7kNvwE84z6-&_nc_oc=AdpwgbQPTY2TQxzf3lN3Ei-h-PNCL_6mqJS0-5sRffApbHVTc8xcynrOgU3gZyVrosI&_nc_ad=z-m&_nc_cid=0&_nc_zt=23&_nc_ht=scontent-sjc6-1.cdninstagram.com&_nc_gid=JMD35m94F_b7pOx4A6UHWg&_nc_ss=7a120&oh=00_Af5RkjMi-q5nWJmDKit30Yqc2u5-WMJn6WzaYaaiErDO0w&oe=6A2083AA",
          "caption": "Cheerio 🎶 \n\nWerkelijk iets aparts❗️\n\n#foryou #cheerio #daanwillemsautomotive #auto #automotive"
        },
        "3900410431447200289": {
          "pk": "3900410431447200289",
          "code": "DYhCp9Eo3Ih",
          "takenAt": 1779185575,
          "mediaType": 2,
          "productType": "clips",
          "likeCount": 65743,
          "commentCount": 594,
          "playCount": 1183354,
          "thumbnail": "https://scontent-sjc6-1.cdninstagram.com/v/t51.71878-15/673815360_27445586585039559_5019819559310173801_n.jpg?stp=dst-jpg_e15_tt6&_nc_cat=100&ig_cache_key=MzkwMDQxMDQzMTQ0NzIwMDI4OQ%3D%3D.3-ccb7-5&ccb=7-5&_nc_sid=58cdad&efg=eyJ2ZW5jb2RlX3RhZyI6IkNMSVBTLnhwaWRzLjY0MC5zZHIudmlkZW9fbmZyYW1lX2NvdmVyX2ZyYW1lLkMzIn0%3D&_nc_ohc=JNbfCIh-Cy8Q7kNvwGDLUeA&_nc_oc=AdqJf1T8i_5nZimhr2k7zdunv5Edejae0UadZc_ezhHzvCRkfib1ohwZdZiRa-GN0_M&_nc_ad=z-m&_nc_cid=0&_nc_zt=23&_nc_ht=scontent-sjc6-1.cdninstagram.com&_nc_gid=JMD35m94F_b7pOx4A6UHWg&_nc_ss=7a120&oh=00_Af4OFiGOT8w09ldnLNRS61G5FBy1xQ1gnU7Eb_Q--19G7g&oe=6A2065A4",
          "caption": "Dit wil je niet missen… 👀🔥\nDe volledige video staat nu op ons YouTube-kanaal! 🎥\n\nCheck de link in bio 🔗\n\nOutfit: @jorcustom KORTINGSCODE: Daan15 \n\n#daanwillemsautomotive #automotive #linkinbio #auto #humor"
        },
        "3895363154944939199": {
          "pk": "3895363154944939199",
          "code": "DYPHCaho1S_",
          "takenAt": 1778583566,
          "mediaType": 2,
          "productType": "clips",
          "likeCount": 6436,
          "commentCount": 69,
          "playCount": 375302,
          "thumbnail": "https://scontent-sjc6-1.cdninstagram.com/v/t51.71878-15/687382090_1481427423767359_6664189255473369608_n.jpg?stp=dst-jpg_e15_tt6&_nc_cat=100&ig_cache_key=Mzg5NTM2MzE1NDk0NDkzOTE5OQ%3D%3D.3-ccb7-5&ccb=7-5&_nc_sid=58cdad&efg=eyJ2ZW5jb2RlX3RhZyI6IkNMSVBTLnhwaWRzLjY0MC5zZHIudmlkZW9fbmZyYW1lX2NvdmVyX2ZyYW1lLkMzIn0%3D&_nc_ohc=IFxOZ85ZojYQ7kNvwGpXfVJ&_nc_oc=AdqSEIZqCGnMB6v5sA9UmAJAPFjQrC7YfaRA33nLmmiOVUxkk-f3yVO8Q5hX-1vMvJY&_nc_ad=z-m&_nc_cid=0&_nc_zt=23&_nc_ht=scontent-sjc6-1.cdninstagram.com&_nc_gid=JMD35m94F_b7pOx4A6UHWg&_nc_ss=7a120&oh=00_Af6fbWkV_xR_8m5lCPoiBAbtMrLrBTaz1dJNJYnU2eZunw&oe=6A207290",
          "caption": "Dit wil je niet missen… 👀🔥\nDe volledige video staat nu op ons YouTube-kanaal! 🎥\n\nCheck de link in bio 🔗\n\n#daanwillemsautomotive #linkinbio #auto #automotive #autodealer"
        },
        "3893358846230111821": {
          "pk": "3893358846230111821",
          "code": "DYH_T4kq6ZN",
          "takenAt": 1778344655,
          "mediaType": 2,
          "productType": "clips",
          "likeCount": 1611,
          "commentCount": 129,
          "playCount": 222104,
          "thumbnail": "https://scontent-sjc6-1.cdninstagram.com/v/t51.71878-15/686536255_986686553754867_1287721811128683474_n.jpg?stp=dst-jpg_e15_tt6&_nc_cat=100&ig_cache_key=Mzg5MzM1ODg0NjIzMDExMTgyMQ%3D%3D.3-ccb7-5&ccb=7-5&_nc_sid=58cdad&efg=eyJ2ZW5jb2RlX3RhZyI6IkNMSVBTLnhwaWRzLjY0MC5zZHIudmlkZW9fbmZyYW1lX2NvdmVyX2ZyYW1lLkMzIn0%3D&_nc_ohc=pNijvE8j3JsQ7kNvwE-IXYD&_nc_oc=Ado9lauUU4UhZC2K3DmY38WrSpLPrKB24gFdrYdlYURGsi_h-39n_pEJTf_HBpSNSAc&_nc_ad=z-m&_nc_cid=0&_nc_zt=23&_nc_ht=scontent-sjc6-1.cdninstagram.com&_nc_gid=JMD35m94F_b7pOx4A6UHWg&_nc_ss=7a120&oh=00_Af4eRDmcbNjKVTG6M4BBUbNdVI-DMpfpkIsgH6X6LYEFbw&oe=6A206A88",
          "caption": "Reageer met ‘Auto’ om de volledige podcast te ontvangen"
        },
        "3892446686729198828": {
          "pk": "3892446686729198828",
          "code": "DYEv6N1o9zs",
          "takenAt": 1778235891,
          "mediaType": 2,
          "productType": "clips",
          "likeCount": 7079,
          "commentCount": 59,
          "playCount": 342419,
          "thumbnail": "https://scontent-sjc3-1.cdninstagram.com/v/t51.71878-15/688065475_1002189139431848_4593210018179984199_n.jpg?stp=dst-jpg_e15_tt6&_nc_cat=106&ig_cache_key=Mzg5MjQ0NjY4NjcyOTE5ODgyOA%3D%3D.3-ccb7-5&ccb=7-5&_nc_sid=58cdad&efg=eyJ2ZW5jb2RlX3RhZyI6IkNMSVBTLnhwaWRzLjY0MC5zZHIudmlkZW9fbmZyYW1lX2NvdmVyX2ZyYW1lLkMzIn0%3D&_nc_ohc=3ZmwxznioAcQ7kNvwG87JsA&_nc_oc=Ado64O_VuyFgOXL5DmEqzswbxM5SuASjD5J4cNP797bgSH8Fk0wWPfEyT6WSSEfIQsI&_nc_ad=z-m&_nc_cid=0&_nc_zt=23&_nc_ht=scontent-sjc3-1.cdninstagram.com&_nc_gid=JMD35m94F_b7pOx4A6UHWg&_nc_ss=7a120&oh=00_Af4ojIV7k1MQwkmOLEXNz61HTCva90YYLzO8m6D4bT2tZw&oe=6A207005",
          "caption": "Kia Picanto • Lage KM • NL auto • Helaas al verkocht! •\n\n#daanwillemsautomotive #auto #automotive #occasion #autodealer"
        },
        "3890256775422927178": {
          "pk": "3890256775422927178",
          "code": "DX89-0AI-FK",
          "takenAt": 1777974898,
          "mediaType": 2,
          "productType": "clips",
          "likeCount": 4307,
          "commentCount": 86,
          "playCount": 329215,
          "thumbnail": "https://scontent-sjc3-1.cdninstagram.com/v/t51.71878-15/691552122_2149563819199422_8643963564606849792_n.jpg?stp=dst-jpg_e15_tt6&_nc_cat=105&ig_cache_key=Mzg5MDI1Njc3NTQyMjkyNzE3OA%3D%3D.3-ccb7-5&ccb=7-5&_nc_sid=58cdad&efg=eyJ2ZW5jb2RlX3RhZyI6IkNMSVBTLnhwaWRzLjY0MC5zZHIudmlkZW9fbmZyYW1lX2NvdmVyX2ZyYW1lLkMzIn0%3D&_nc_ohc=Gn5TcUESKsMQ7kNvwG8e2Nm&_nc_oc=Ado6nlKLIXNnJ-o6L7QC7efXQiplml3wwnYeZk-V2bdd-mJscItdKK9PGXF3ujytrEk&_nc_ad=z-m&_nc_cid=0&_nc_zt=23&_nc_ht=scontent-sjc3-1.cdninstagram.com&_nc_gid=JMD35m94F_b7pOx4A6UHWg&_nc_ss=7a120&oh=00_Af6UTuNK7sqo-BGJUJI8AodwizMJ-aazZV7ZJlkqNUETTQ&oe=6A2075DF",
          "caption": "WIE O WIE GAAN Wij ZIEN 👀❓❗️\n\nLijkt het je interessant om samen iets bijzonders neer te zetten?\nStuur ons een bericht en wie weet staan wij binnenkort bij jullie op locatie 🎥\n\n#daanwillemsautomotive"
        },
        "3890167375595136294": {
          "pk": "3890167375595136294",
          "code": "DX8pp37KWUm",
          "takenAt": 1777964423,
          "mediaType": 2,
          "productType": "clips",
          "likeCount": 1311,
          "commentCount": 607,
          "playCount": 158178,
          "thumbnail": "https://scontent-sjc3-1.cdninstagram.com/v/t51.71878-15/683583452_1267611602233812_7254574104103606005_n.jpg?stp=dst-jpg_e15_tt6&_nc_cat=105&ig_cache_key=Mzg5MDE2NzM3NTU5NTEzNjI5NA%3D%3D.3-ccb7-5&ccb=7-5&_nc_sid=58cdad&efg=eyJ2ZW5jb2RlX3RhZyI6IkNMSVBTLnhwaWRzLjY0MC5zZHIudmlkZW9fZGVmYXVsdF9jb3Zlcl9mcmFtZS5DMyJ9&_nc_ohc=Fet5xLZqoSUQ7kNvwErJbjU&_nc_oc=AdogVTWhCZ7XZncTGLAlV79nq5ynoU6UgH2GcD4ls_1Yd0L6vy97Gbbb0FaadSkypOs&_nc_ad=z-m&_nc_cid=0&_nc_zt=23&_nc_ht=scontent-sjc3-1.cdninstagram.com&_nc_gid=JMD35m94F_b7pOx4A6UHWg&_nc_ss=7a120&oh=00_Af4ljJXm7ow99t9WZW8uaPozf4hVHAjgc6daxbG31TcTFg&oe=6A205A7E",
          "caption": "Comment ‘AUTO’ en we sturen je de volledige podcast.\n\nEen branche met 1% marge… en toch bouwen zij aan miljoenenbedrijven.\n\nIn deze aflevering zit we met zes ondernemers uit de autobranche aan tafel. Je hoort hoe zij opereren in een markt waar de meeste mensen het niet redden, wat er écht gebeurt achter de schermen en waarom juist hier het verschil wordt gemaakt. \n\nBenieuwd hoe je wint in een markt waar bijna niemand wint? Check dan nu de aflevering op YouTube & Spotify. 🚗🔥"
        },
        "3889723293121066135": {
          "pk": "3889723293121066135",
          "code": "DX7Ern5CzSX",
          "takenAt": 1777911284,
          "mediaType": 2,
          "productType": "clips",
          "likeCount": 14878,
          "commentCount": 68,
          "playCount": 545799,
          "thumbnail": "https://scontent-sjc6-1.cdninstagram.com/v/t51.71878-15/684079083_896948866696012_3011223092327894952_n.jpg?stp=dst-jpg_e15_tt6&_nc_cat=100&ig_cache_key=Mzg4OTcyMzI5MzEyMTA2NjEzNQ%3D%3D.3-ccb7-5&ccb=7-5&_nc_sid=58cdad&efg=eyJ2ZW5jb2RlX3RhZyI6IkNMSVBTLnhwaWRzLjY0MC5zZHIudmlkZW9fbmZyYW1lX2NvdmVyX2ZyYW1lLkMzIn0%3D&_nc_ohc=zyU2759cKpAQ7kNvwFQfxP_&_nc_oc=AdoyZRS0pR3wRBK6Q9ByrE5JD95bcrLv8dESnLNwBkD5r8KyJhoe3qCS7WTYiGQyzSQ&_nc_ad=z-m&_nc_cid=0&_nc_zt=23&_nc_ht=scontent-sjc6-1.cdninstagram.com&_nc_gid=JMD35m94F_b7pOx4A6UHWg&_nc_ss=7a120&oh=00_Af42tVYYgDd-Hz4hoRz-zS43Wuz3sSw0bFbpDlY55v0YbA&oe=6A207F44",
          "caption": "@daanwillemsautomotive en ik deden een wijnproeverij, de hele video zie je op mijn YT kanaal: raulgroenenyoutube"
        }
      }
    }
  }
}
